deepsafe/__init__.py
deepsafe-0.0.1.dist-info/LICENSE
deepsafe-0.0.1.dist-info/METADATA
deepsafe-0.0.1.dist-info/WHEEL
deepsafe-0.0.1.dist-info/top_level.txt
deepsafe-0.0.1.dist-info/RECORD
